moceansdk/__init__.py
moceansdk/auth/__init__.py
moceansdk/auth/basic.py
moceansdk/exceptions/__init__.py
moceansdk/modules/__init__.py
moceansdk/modules/response_factory.py
moceansdk/modules/transmitter.py
moceansdk/modules/account/__init__.py
moceansdk/modules/account/balance.py
moceansdk/modules/account/pricing.py
moceansdk/modules/command/__init__.py
moceansdk/modules/command/channel.py
moceansdk/modules/command/command.py
moceansdk/modules/command/mc.py
moceansdk/modules/command/mc_builder.py
moceansdk/modules/command/mc_object/__init__.py
moceansdk/modules/command/mc_object/contact_type.py
moceansdk/modules/command/mc_object/send_sms.py
moceansdk/modules/command/mc_object/tg_request_contact.py
moceansdk/modules/command/mc_object/tg_send_animation.py
moceansdk/modules/command/mc_object/tg_send_audio.py
moceansdk/modules/command/mc_object/tg_send_document.py
moceansdk/modules/command/mc_object/tg_send_photo.py
moceansdk/modules/command/mc_object/tg_send_text.py
moceansdk/modules/command/mc_object/tg_send_video.py
moceansdk/modules/message/__init__.py
moceansdk/modules/message/channel.py
moceansdk/modules/message/message_status.py
moceansdk/modules/message/sms.py
moceansdk/modules/message/verify_request.py
moceansdk/modules/message/verify_validate.py
moceansdk/modules/number_lookup/__init__.py
moceansdk/modules/number_lookup/number_lookup.py
moceansdk/modules/voice/__init__.py
moceansdk/modules/voice/mc.py
moceansdk/modules/voice/mc_builder.py
moceansdk/modules/voice/voice.py
moceansdk/modules/voice/mc_object/__init__.py
moceansdk/modules/voice/mc_object/collect.py
moceansdk/modules/voice/mc_object/dial.py
moceansdk/modules/voice/mc_object/play.py
moceansdk/modules/voice/mc_object/record.py
moceansdk/modules/voice/mc_object/say.py
moceansdk/modules/voice/mc_object/sleep.py
moceansdk-1.2.0.dist-info/LICENSE.txt
moceansdk-1.2.0.dist-info/METADATA
moceansdk-1.2.0.dist-info/WHEEL
moceansdk-1.2.0.dist-info/top_level.txt
moceansdk-1.2.0.dist-info/RECORD
