Metadata-Version: 2.1
Name: moceansdk
Version: 1.2.0
Summary: Mocean Client Library for Python
Home-page: https://github.com/MoceanAPI/mocean-sdk-python
Author: Micro Ocean Technologies Sdn Bhd
Author-email: support@moceanapi.com
License: MIT
Platform: any
Classifier: Programming Language :: Python :: 3.8
Classifier: Programming Language :: Python :: 3.9
Classifier: Programming Language :: Python :: 3.10
Classifier: Programming Language :: Python :: 3.11
Classifier: Programming Language :: Python :: 3.12
Provides-Extra: test
License-File: LICENSE.txt
